streamlit_custom_tooltip/__init__.py
streamlit_custom_tooltip/frontend/build/asset-manifest.json
streamlit_custom_tooltip/frontend/build/bootstrap.min.css
streamlit_custom_tooltip/frontend/build/index.html
streamlit_custom_tooltip/frontend/build/precache-manifest.093fc6e1f0fd057775c4c5e0e232c0c5.js
streamlit_custom_tooltip/frontend/build/precache-manifest.3b0c9c4a9b075faadb3ac6bd6a1d4705.js
streamlit_custom_tooltip/frontend/build/precache-manifest.98e59efd9e6379f0ef89f1002eeddc79.js
streamlit_custom_tooltip/frontend/build/service-worker.js
streamlit_custom_tooltip/frontend/build/static/js/2.1afb79ed.chunk.js
streamlit_custom_tooltip/frontend/build/static/js/2.1afb79ed.chunk.js.LICENSE.txt
streamlit_custom_tooltip/frontend/build/static/js/2.1afb79ed.chunk.js.map
streamlit_custom_tooltip/frontend/build/static/js/main.443adc67.chunk.js
streamlit_custom_tooltip/frontend/build/static/js/main.443adc67.chunk.js.LICENSE.txt
streamlit_custom_tooltip/frontend/build/static/js/main.443adc67.chunk.js.map
streamlit_custom_tooltip/frontend/build/static/js/main.8a988e39.chunk.js
streamlit_custom_tooltip/frontend/build/static/js/main.8a988e39.chunk.js.LICENSE.txt
streamlit_custom_tooltip/frontend/build/static/js/main.8a988e39.chunk.js.map
streamlit_custom_tooltip/frontend/build/static/js/main.e9ec8551.chunk.js
streamlit_custom_tooltip/frontend/build/static/js/main.e9ec8551.chunk.js.LICENSE.txt
streamlit_custom_tooltip/frontend/build/static/js/main.e9ec8551.chunk.js.map
streamlit_custom_tooltip/frontend/build/static/js/runtime-main.72427be0.js
streamlit_custom_tooltip/frontend/build/static/js/runtime-main.72427be0.js.map
streamlit_custom_tooltip-0.2.0.dist-info/LICENSE
streamlit_custom_tooltip-0.2.0.dist-info/METADATA
streamlit_custom_tooltip-0.2.0.dist-info/WHEEL
streamlit_custom_tooltip-0.2.0.dist-info/top_level.txt
streamlit_custom_tooltip-0.2.0.dist-info/RECORD
