Metadata-Version: 2.1
Name: streamlit-custom-tooltip
Version: 0.2.0
Summary: UNKNOWN
Home-page: UNKNOWN
Author: ANelson
Author-email: 
License: UNKNOWN
Platform: UNKNOWN
Requires-Python: >=3.6
Requires-Dist: streamlit (>=0.63)
